a_config/__init__.py
a_config/asgi.py
a_config/settings.py
a_config/urls.py
a_config/wsgi.py
django_visitor_tracker/__init__.py
django_visitor_tracker/admin.py
django_visitor_tracker/apps.py
django_visitor_tracker/middleware.py
django_visitor_tracker/models.py
django_visitor_tracker/tests.py
django_visitor_tracker/urls.py
django_visitor_tracker/utils.py
django_visitor_tracker/views.py
django_visitor_tracker/migrations/0001_initial.py
django_visitor_tracker/migrations/0002_alter_logentry_timestamp.py
django_visitor_tracker/migrations/__init__.py
django_visitor_tracker/templates/admin/django_visitor_tracker/logentry/change_list.html
django_visitor_tracker-0.1.0.dist-info/licenses/LICENSE
django_visitor_tracker-0.1.0.dist-info/METADATA
django_visitor_tracker-0.1.0.dist-info/WHEEL
django_visitor_tracker-0.1.0.dist-info/top_level.txt
django_visitor_tracker-0.1.0.dist-info/RECORD
