Metadata-Version: 2.4
Name: django-visitor-tracker
Version: 0.1.0
Summary: Visitor tracking middleware for Django with admin charts
Home-page: https://github.com/ventuno-21/django-visitor-tracker
Author: Ventuno
Classifier: Framework :: Django
Classifier: Programming Language :: Python :: 3
Classifier: License :: OSI Approved :: MIT License
Requires-Python: >=3.8
License-File: LICENSE
Requires-Dist: Django>=3.2
Requires-Dist: matplotlib
Requires-Dist: user-agents
Dynamic: author
Dynamic: classifier
Dynamic: description
Dynamic: description-content-type
Dynamic: home-page
Dynamic: license-file
Dynamic: requires-dist
Dynamic: requires-python
Dynamic: summary
